MANIFEST.in
setup.py
centinel/__init__.py
centinel/backend.py
centinel/cli.py
centinel/client.py
centinel/command.py
centinel/config.py
centinel/daemonize.py
centinel/experiment.py
centinel/utils.py
centinel/data/country.txt
centinel/data/dns_example.txt
centinel/data/http_request.txt
centinel/data/input_1.txt
centinel/data/input_2.txt
centinel/data/ping.txt
centinel/data/ssl_strip.txt
centinel/data/tcp_connect.txt
centinel/data/tls.txt
centinel/data/traceroute.txt
centinel/data/turkey.txt
centinel/data/world.txt
centinel/experiments/baseline.py
centinel/experiments/baseline_linear.py
centinel/experiments/check_tls_fprs.py
centinel/experiments/example_dns_exp.py
centinel/experiments/http_request.py
centinel/experiments/multi_input.py
centinel/experiments/ping.py
centinel/experiments/ssl_strip.py
centinel/experiments/tcp_connect.py
centinel/experiments/traceroute.py
centinel/experiments/turkey.py
centinel/primitives/__init__.py
centinel/primitives/dnslib.py
centinel/primitives/http.py
centinel/primitives/http_helper.py
centinel/primitives/tcpdump.py
centinel/primitives/tls.py
centinel/primitives/traceroute.py
centinel/vpn/__init__.py
centinel/vpn/cli.py
centinel/vpn/hma.py
centinel/vpn/openvpn.py
centinel_dev.egg-info/PKG-INFO
centinel_dev.egg-info/SOURCES.txt
centinel_dev.egg-info/dependency_links.txt
centinel_dev.egg-info/entry_points.txt
centinel_dev.egg-info/requires.txt
centinel_dev.egg-info/top_level.txt